carla_utils/__init__.py
carla_utils/__pycache__/__init__.cpython-37.pyc
carla_utils/augment/__init__.py
carla_utils/augment/curve.py
carla_utils/augment/env_info.py
carla_utils/augment/global_path.py
carla_utils/augment/inner_convert.py
carla_utils/augment/lane_path.py
carla_utils/augment/obstacle.py
carla_utils/augment/obstacle_array.py
carla_utils/augment/obstacle_predict.py
carla_utils/augment/road_path.py
carla_utils/augment/state.py
carla_utils/augment/station.py
carla_utils/augment/tools.py
carla_utils/augment/trajectory.py
carla_utils/augment/waypoint.py
carla_utils/augment/__pycache__/__init__.cpython-37.pyc
carla_utils/augment/__pycache__/curve.cpython-37.pyc
carla_utils/augment/__pycache__/env_info.cpython-37.pyc
carla_utils/augment/__pycache__/global_path.cpython-37.pyc
carla_utils/augment/__pycache__/inner_convert.cpython-37.pyc
carla_utils/augment/__pycache__/lane_path.cpython-37.pyc
carla_utils/augment/__pycache__/obstacle.cpython-37.pyc
carla_utils/augment/__pycache__/obstacle_array.cpython-37.pyc
carla_utils/augment/__pycache__/obstacle_predict.cpython-37.pyc
carla_utils/augment/__pycache__/road_path.cpython-37.pyc
carla_utils/augment/__pycache__/state.cpython-37.pyc
carla_utils/augment/__pycache__/station.cpython-37.pyc
carla_utils/augment/__pycache__/tools.cpython-37.pyc
carla_utils/augment/__pycache__/trajectory.cpython-37.pyc
carla_utils/augment/__pycache__/waypoint.cpython-37.pyc
carla_utils/basic/__init__.py
carla_utils/basic/coordinate_transformation.py
carla_utils/basic/pc_visualizer.py
carla_utils/basic/tools.py
carla_utils/basic/__pycache__/__init__.cpython-37.pyc
carla_utils/basic/__pycache__/coordinate_transformation.cpython-37.pyc
carla_utils/basic/__pycache__/pc_visualizer.cpython-37.pyc
carla_utils/basic/__pycache__/tools.cpython-37.pyc
carla_utils/basic/functions/quintic.py
carla_utils/basic/functions/spiral.py
carla_utils/basic/functions/__pycache__/quintic.cpython-37.pyc
carla_utils/basic/functions/__pycache__/spiral.cpython-37.pyc
carla_utils-0.0.2.dist-info/LICENSE
carla_utils-0.0.2.dist-info/METADATA
carla_utils-0.0.2.dist-info/WHEEL
carla_utils-0.0.2.dist-info/top_level.txt
carla_utils-0.0.2.dist-info/RECORD
